fsm_modal_analysis.py
fsm_modal_analysis-1.0.3.dist-info/DESCRIPTION.rst
fsm_modal_analysis-1.0.3.dist-info/METADATA
fsm_modal_analysis-1.0.3.dist-info/RECORD
fsm_modal_analysis-1.0.3.dist-info/WHEEL
fsm_modal_analysis-1.0.3.dist-info/entry_points.txt
fsm_modal_analysis-1.0.3.dist-info/metadata.json
fsm_modal_analysis-1.0.3.dist-info/top_level.txt
