Metadata-Version: 2.0
Name: fsm-modal-analysis
Version: 1.0.3
Summary: Console app and Python API for visualization and modal analysis of the parametric model of buckling and free vibration in prismatic shell structures, as computed by the fsm_eigenvalue project.
Home-page: https://github.com/petarmaric/fsm_modal_analysis
Author: Petar Maric
Author-email: petarmaric@uns.ac.rs
License: BSD
Platform: any
Classifier: Development Status :: 5 - Production/Stable
Classifier: Environment :: Console
Classifier: Intended Audience :: Developers
Classifier: Intended Audience :: Science/Research
Classifier: License :: OSI Approved :: BSD License
Classifier: Operating System :: OS Independent
Classifier: Programming Language :: Python :: 2.7
Classifier: Topic :: Scientific/Engineering
Classifier: Topic :: Scientific/Engineering :: Physics
Requires-Dist: fsm-load-modal-composites (~=1.0)
Requires-Dist: matplotlib (~=2.1)
Requires-Dist: numpy (~=1.11)
